setup.py
JzStock.egg-info/PKG-INFO
JzStock.egg-info/SOURCES.txt
JzStock.egg-info/dependency_links.txt
JzStock.egg-info/top_level.txt
Utility/ChinaStockUtil.py
Utility/__init__.py