Metadata-Version: 1.0
Name: JzStock
Version: 0.2
Summary: JzStock is an elegant and simple Stock library for Python.
Home-page: UNKNOWN
Author: eric.ni
Author-email: eric.ni@ijinzhuan.com
License: MIT License
Keywords: Stock,Stock Tools
Platform: any
